{
  "name": "upstream-bitwise-auto-inventory",
  "version": "1",
  "family": "bitwise",
  "source": "third_party/execution-specs/tests/benchmark/compute/instruction/test_bitwise.py",
  "entries": [
    {
      "upstream_ref": "tests/benchmark/compute/instruction/test_bitwise.py::test_bitwise[opcode=AND]",
      "case_id": "upstream.benchmark.bitwise.test_bitwise.and",
      "admitted": true,
      "mode": "test_bitwise",
      "reasons": [],
      "source": "test_bitwise",
      "opcode": "AND",
      "args": [
        115792089237316195423570985008687907853269984665640564039457584007908834671663,
        52435875175126190479447740508185965837690552500527637822603658699938581184513
      ]
    },
    {
      "upstream_ref": "tests/benchmark/compute/instruction/test_bitwise.py::test_bitwise[opcode=BYTE]",
      "case_id": "upstream.benchmark.bitwise.test_bitwise.byte",
      "admitted": true,
      "mode": "test_bitwise",
      "reasons": [],
      "source": "test_bitwise",
      "opcode": "BYTE",
      "args": [
        31,
        115792089237316195423570985008687907853269984665640564039457584007908834671663
      ]
    },
    {
      "upstream_ref": "tests/benchmark/compute/instruction/test_bitwise.py::test_bitwise[opcode=OR]",
      "case_id": "upstream.benchmark.bitwise.test_bitwise.or",
      "admitted": true,
      "mode": "test_bitwise",
      "reasons": [],
      "source": "test_bitwise",
      "opcode": "OR",
      "args": [
        115792089237316195423570985008687907853269984665640564039457584007908834671663,
        52435875175126190479447740508185965837690552500527637822603658699938581184513
      ]
    },
    {
      "upstream_ref": "tests/benchmark/compute/instruction/test_bitwise.py::test_bitwise[opcode=SAR]",
      "case_id": "upstream.benchmark.bitwise.test_bitwise.sar",
      "admitted": true,
      "mode": "test_bitwise",
      "reasons": [],
      "source": "test_bitwise",
      "opcode": "SAR",
      "args": [
        1,
        115792089237316195423570985008687907853269984665640564039457584007908834671663
      ]
    },
    {
      "upstream_ref": "tests/benchmark/compute/instruction/test_bitwise.py::test_bitwise[opcode=SHL]",
      "case_id": "upstream.benchmark.bitwise.test_bitwise.shl",
      "admitted": true,
      "mode": "test_bitwise",
      "reasons": [],
      "source": "test_bitwise",
      "opcode": "SHL",
      "args": [
        1,
        115792089237316195423570985008687907853269984665640564039457584007908834671663
      ]
    },
    {
      "upstream_ref": "tests/benchmark/compute/instruction/test_bitwise.py::test_bitwise[opcode=SHR]",
      "case_id": "upstream.benchmark.bitwise.test_bitwise.shr",
      "admitted": true,
      "mode": "test_bitwise",
      "reasons": [],
      "source": "test_bitwise",
      "opcode": "SHR",
      "args": [
        1,
        115792089237316195423570985008687907853269984665640564039457584007908834671663
      ]
    },
    {
      "upstream_ref": "tests/benchmark/compute/instruction/test_bitwise.py::test_bitwise[opcode=XOR]",
      "case_id": "upstream.benchmark.bitwise.test_bitwise.xor",
      "admitted": true,
      "mode": "test_bitwise",
      "reasons": [],
      "source": "test_bitwise",
      "opcode": "XOR",
      "args": [
        115792089237316195423570985008687907853269984665640564039457584007908834671663,
        52435875175126190479447740508185965837690552500527637822603658699938581184513
      ]
    },
    {
      "upstream_ref": "tests/benchmark/compute/instruction/test_bitwise.py::test_clz_diff",
      "case_id": "upstream.benchmark.bitwise.test_clz_diff.clz",
      "admitted": false,
      "mode": null,
      "reasons": [
        "requires gas-sensitive benchmark shape not yet mapped"
      ],
      "source": "test_clz_diff",
      "opcode": null,
      "args": null
    },
    {
      "upstream_ref": "tests/benchmark/compute/instruction/test_bitwise.py::test_clz_same",
      "case_id": "upstream.benchmark.bitwise.test_clz_same.clz",
      "admitted": true,
      "mode": "test_clz_same",
      "reasons": [],
      "source": "test_clz_same",
      "opcode": "CLZ",
      "args": [
        248
      ]
    },
    {
      "upstream_ref": "tests/benchmark/compute/instruction/test_bitwise.py::test_not_op",
      "case_id": "upstream.benchmark.bitwise.test_not_op.not",
      "admitted": true,
      "mode": "test_not_op",
      "reasons": [],
      "source": "test_not_op",
      "opcode": "NOT",
      "args": [
        0
      ]
    },
    {
      "upstream_ref": "tests/benchmark/compute/instruction/test_bitwise.py::test_shifts[opcode=SAR]",
      "case_id": "upstream.benchmark.bitwise.test_shifts.sar",
      "admitted": true,
      "mode": "test_shifts",
      "reasons": [],
      "source": "test_shifts",
      "opcode": "SAR",
      "args": []
    },
    {
      "upstream_ref": "tests/benchmark/compute/instruction/test_bitwise.py::test_shifts[opcode=SHR]",
      "case_id": "upstream.benchmark.bitwise.test_shifts.shr",
      "admitted": true,
      "mode": "test_shifts",
      "reasons": [],
      "source": "test_shifts",
      "opcode": "SHR",
      "args": []
    }
  ]
}
